<?xml version="1.0" encoding="UTF-8"?>
<objects serializationModel="Studio.02.02.00">
	<object class="AudioFile" id="{199a97c4-c0d2-4723-8c6a-cd38d970b38e}">
		<property name="assetPath">
			<value>SFX/SFX/Animals/animal-monkey-vervet-screech-02.wav</value>
		</property>
		<property name="frequencyInKHz">
			<value>48</value>
		</property>
		<property name="channelCount">
			<value>2</value>
		</property>
		<property name="length">
			<value>1.3349791666666666</value>
		</property>
		<relationship name="masterAssetFolder">
			<destination>{84fa4b84-f4b2-4178-9c73-227fd678a014}</destination>
		</relationship>
	</object>
</objects>
