<?xml version="1.0" encoding="UTF-8"?>
<objects serializationModel="Studio.02.02.00">
	<object class="AudioFile" id="{e2ef668f-8340-4c3d-a68c-202c79600c7b}">
		<property name="assetPath">
			<value>SFX/SFX/Machines/construction-machine-exterior-plunge-router-01.wav</value>
		</property>
		<property name="isStreaming">
			<value>true</value>
		</property>
		<property name="frequencyInKHz">
			<value>48</value>
		</property>
		<property name="channelCount">
			<value>2</value>
		</property>
		<property name="length">
			<value>11.006979166666667</value>
		</property>
		<relationship name="masterAssetFolder">
			<destination>{84fa4b84-f4b2-4178-9c73-227fd678a014}</destination>
		</relationship>
	</object>
</objects>
