<?xml version="1.0" encoding="UTF-8"?>
<objects serializationModel="Studio.02.02.00">
	<object class="AudioFile" id="{eea7f5e3-6741-43e6-9281-02b4c5839a57}">
		<property name="assetPath">
			<value>FoleySounds 18.04/Page turn.wav</value>
		</property>
		<property name="frequencyInKHz">
			<value>44.0999985</value>
		</property>
		<property name="channelCount">
			<value>2</value>
		</property>
		<property name="length">
			<value>1.5</value>
		</property>
		<relationship name="masterAssetFolder">
			<destination>{84fa4b84-f4b2-4178-9c73-227fd678a014}</destination>
		</relationship>
	</object>
</objects>
