{"inkVersion":21,"root":[["#","^speaker: Conspiracy_Theorist","/#","^\"Good evening, fellow prisoner!\"","\n",["ev",{"^->":"0.5.$r1"},{"temp=":"$r"},"str",{"->":".^.s"},[{"#n":"$r1"}],"/str","/ev",{"*":"0.c-0","flg":18},{"s":["^Good evening.",{"->":"$r","var":true},null]}],["ev",{"^->":"0.6.$r1"},{"temp=":"$r"},"str",{"->":".^.s"},[{"#n":"$r1"}],"/str","/ev",{"*":"0.c-1","flg":18},{"s":["^Prisoner? Son, I am an intern!",{"->":"$r","var":true},null]}],{"c-0":["ev",{"^->":"0.c-0.$r2"},"/ev",{"temp=":"$r"},{"->":"0.5.s"},[{"#n":"$r2"}],"\n",{"->":"polite"},{"->":"0.g-0"},{"#f":5}],"c-1":["ev",{"^->":"0.c-1.$r2"},"/ev",{"temp=":"$r"},{"->":"0.6.s"},[{"#n":"$r2"}],"\n",{"->":"intern"},{"->":"0.g-0"},{"#f":5}],"g-0":["done",{"#f":5}]}],"done",{"intern":[["^\"You really roll like my old man. Honest in heart, but blank in the bulb. You see, I am not wearing this jumpsuit voluntarily, nor am I an Intern. It's the same as yours by the way.\"","\n",["ev",{"^->":"intern.0.2.$r1"},{"temp=":"$r"},"str",{"->":".^.s"},[{"#n":"$r1"}],"/str","/ev",{"*":".^.^.c-0","flg":18},{"s":["^Continue",{"->":"$r","var":true},null]}],{"c-0":["ev",{"^->":"intern.0.c-0.$r2"},"/ev",{"temp=":"$r"},{"->":".^.^.2.s"},[{"#n":"$r2"}],"\n",{"->":"polite"},{"#f":5}]}],{"#f":1}],"polite":[["^\"I see, you just passed your application, hm? I bet you were \"phenomenal\" and did \"exceptionally\" well.\"","\n",["ev",{"^->":"polite.0.2.$r1"},{"temp=":"$r"},"str",{"->":".^.s"},[{"#n":"$r1"}],"/str","/ev",{"*":".^.^.c-0","flg":18},{"s":["^I don't like to show off, but since you've asked..",{"->":"$r","var":true},null]}],["ev",{"^->":"polite.0.3.$r1"},{"temp=":"$r"},"str",{"->":".^.s"},[{"#n":"$r1"}],"/str","/ev",{"*":".^.^.c-1","flg":18},{"s":["^I get the feeling I wasn't the only one?",{"->":"$r","var":true},null]}],["ev",{"^->":"polite.0.4.$r1"},{"temp=":"$r"},"str",{"->":".^.s"},[{"#n":"$r1"}],"/str","/ev",{"*":".^.^.c-2","flg":18},{"s":["^Oh, actually I'm just having a peak.",{"->":"$r","var":true},null]}],{"c-0":["ev",{"^->":"polite.0.c-0.$r2"},"/ev",{"temp=":"$r"},{"->":".^.^.2.s"},[{"#n":"$r2"}],"\n",{"->":"Dumb"},{"#f":5}],"c-1":["ev",{"^->":"polite.0.c-1.$r2"},"/ev",{"temp=":"$r"},{"->":".^.^.3.s"},[{"#n":"$r2"}],"\n",{"->":"Like"},{"#f":5}],"c-2":["ev",{"^->":"polite.0.c-2.$r2"},"/ev",{"temp=":"$r"},{"->":".^.^.4.s"},[{"#n":"$r2"}],"\n",{"->":"No"},{"#f":5}]}],{"#f":1}],"No":[["^\"Oh wow, you fell for that line?\"","\n",["ev",{"^->":"No.0.2.$r1"},{"temp=":"$r"},"str",{"->":".^.s"},[{"#n":"$r1"}],"/str","/ev",{"*":"No.0.c-0","flg":18},{"s":["^Continue",{"->":"$r","var":true},null]}],{"c-0":["ev",{"^->":"No.0.c-0.$r2"},"/ev",{"temp=":"$r"},{"->":"No.0.2.s"},[{"#n":"$r2"}],"\n",{"->":"Say_Anything"},{"#f":5}]}],{"#f":1}],"Dumb":[["^\"Ha! Only way you show off, is like a dead fish on the surface!\"","\n",["ev",{"^->":"Dumb.0.2.$r1"},{"temp=":"$r"},"str",{"->":".^.s"},[{"#n":"$r1"}],"/str","/ev",{"*":".^.^.c-0","flg":18},{"s":["^Continue",{"->":"$r","var":true},null]}],{"c-0":["ev",{"^->":"Dumb.0.c-0.$r2"},"/ev",{"temp=":"$r"},{"->":".^.^.2.s"},[{"#n":"$r2"}],"\n",{"->":"Say_Anything"},{"#f":5}]}],{"#f":1}],"Like":[["^\"I like the way you're thinking!\"","\n",["ev",{"^->":"Like.0.2.$r1"},{"temp=":"$r"},"str",{"->":".^.s"},[{"#n":"$r1"}],"/str","/ev",{"*":".^.^.c-0","flg":18},{"s":["^Continue",{"->":"$r","var":true},null]}],{"c-0":["ev",{"^->":"Like.0.c-0.$r2"},"/ev",{"temp=":"$r"},{"->":".^.^.2.s"},[{"#n":"$r2"}],"\n",{"->":"Say_Anything"},{"#f":5}]}],{"#f":1}],"Say_Anything":[["^\"They say anything to get you in here, really. Point is, you wanne be anywhere, but here.\"","\n",["ev",{"^->":"Say_Anything.0.2.$r1"},{"temp=":"$r"},"str",{"->":".^.s"},[{"#n":"$r1"}],"/str","/ev",{"*":".^.^.c-0","flg":18},{"s":["^Yes, the interior is distasteful!",{"->":"$r","var":true},null]}],["ev",{"^->":"Say_Anything.0.3.$r1"},{"temp=":"$r"},"str",{"->":".^.s"},[{"#n":"$r1"}],"/str","/ev",{"*":".^.^.c-1","flg":18},{"s":["^Whats so awful about this place?",{"->":"$r","var":true},null]}],{"c-0":["ev",{"^->":"Say_Anything.0.c-0.$r2"},"/ev",{"temp=":"$r"},{"->":".^.^.2.s"},[{"#n":"$r2"}],"\n",{"->":"NotWhatIMeant"},{"#f":5}],"c-1":["ev",{"^->":"Say_Anything.0.c-1.$r2"},"/ev",{"temp=":"$r"},{"->":".^.^.3.s"},[{"#n":"$r2"}],"\n",{"->":"AboutPlace"},{"#f":5}]}],{"#f":1}],"NotWhatIMeant":[["^\"Hehheh, good one! Ehm..., well, as a matter of fact, i quite like it.\"","\n",["ev",{"^->":"NotWhatIMeant.0.2.$r1"},{"temp=":"$r"},"str",{"->":".^.s"},[{"#n":"$r1"}],"/str","/ev",{"*":".^.^.c-0","flg":18},{"s":["^Sorry?",{"->":"$r","var":true},null]}],{"c-0":["ev",{"^->":"NotWhatIMeant.0.c-0.$r2"},"/ev",{"temp=":"$r"},{"->":".^.^.2.s"},[{"#n":"$r2"}],"\n",{"->":"Bunker"},{"#f":5}]}],{"#f":1}],"Bunker":[["^\"I wouldn't fit the prejudice, if I didn't have a shelter in my garden, right? So, yeah. looks quite familiar. I've hung up some curtains, though.\"","\n",["ev",{"^->":"Bunker.0.2.$r1"},{"temp=":"$r"},"str",{"->":".^.s"},[{"#n":"$r1"}],"/str","/ev",{"*":".^.^.c-0","flg":18},{"s":["^Okay, back to the topic: What about this place?",{"->":"$r","var":true},null]}],{"c-0":["ev",{"^->":"Bunker.0.c-0.$r2"},"/ev",{"temp=":"$r"},{"->":".^.^.2.s"},[{"#n":"$r2"}],"\n",{"->":"AboutPlace"},{"#f":5}]}],{"#f":1}],"AboutPlace":[["^\"First: they throw you in here for any reason. Second: no one really is working here. So, I GUESS we fill a rather passive purpose, not to say: we are beeing kept!\"","\n",["ev",{"^->":"AboutPlace.0.2.$r1"},{"temp=":"$r"},"str",{"->":".^.s"},[{"#n":"$r1"}],"/str","/ev",{"*":".^.^.c-0","flg":18},{"s":["^Continue",{"->":"$r","var":true},null]}],{"c-0":["ev",{"^->":"AboutPlace.0.c-0.$r2"},"/ev",{"temp=":"$r"},{"->":".^.^.2.s"},[{"#n":"$r2"}],"\n",{"->":"GoOn"},{"#f":5}]}],{"#f":1}],"GoOn":[["^\"And the wind never sounded so much like screams to me before!\"","\n",["ev",{"^->":"GoOn.0.2.$r1"},{"temp=":"$r"},"str",{"->":".^.s"},[{"#n":"$r1"}],"/str","/ev",{"*":".^.^.c-0","flg":18},{"s":["^Give me that conclusion.",{"->":"$r","var":true},null]}],{"c-0":["ev",{"^->":"GoOn.0.c-0.$r2"},"/ev",{"temp=":"$r"},{"->":".^.^.2.s"},[{"#n":"$r2"}],"\n",{"->":"Conclusion"},{"#f":5}]}],{"#f":1}],"Conclusion":[["^\"This is not a place any of us should be and we need to get out of here, ASAP! I did some research and came up with some theories myself. You could do your part and help me with some investigations.\"","\n",["ev",{"^->":"Conclusion.0.2.$r1"},{"temp=":"$r"},"str",{"->":".^.s"},[{"#n":"$r1"}],"/str","/ev",{"*":".^.^.c-0","flg":18},{"s":["^About your theories..",{"->":"$r","var":true},null]}],["ev",{"^->":"Conclusion.0.3.$r1"},{"temp=":"$r"},"str",{"->":".^.s"},[{"#n":"$r1"}],"/str","/ev",{"*":".^.^.c-1","flg":18},{"s":["^Okay, what can I do?",{"->":"$r","var":true},null]}],{"c-0":["ev",{"^->":"Conclusion.0.c-0.$r2"},"/ev",{"temp=":"$r"},{"->":".^.^.2.s"},[{"#n":"$r2"}],"\n",{"->":"Theories"},{"#f":5}],"c-1":["ev",{"^->":"Conclusion.0.c-1.$r2"},"/ev",{"temp=":"$r"},{"->":".^.^.3.s"},[{"#n":"$r2"}],"\n",{"->":"ToDo"},{"#f":5}]}],{"#f":1}],"Theories":[["^\"First: did you feet something strange about the way the shady figurre in the lobby was talking, too? To many allusions, right?\"","\n",["ev",{"^->":"Theories.0.2.$r1"},{"temp=":"$r"},"str",{"->":".^.s"},[{"#n":"$r1"}],"/str","/ev",{"*":".^.^.c-0","flg":18},{"s":["^Yep, his behaivor was suspicious.",{"->":"$r","var":true},null]}],["ev",{"^->":"Theories.0.3.$r1"},{"temp=":"$r"},"str",{"->":".^.s"},[{"#n":"$r1"}],"/str","/ev",{"*":".^.^.c-1","flg":18},{"s":["^I do enjoy some poetic phrasing from time to time.",{"->":"$r","var":true},null]}],["ev",{"^->":"Theories.0.4.$r1"},{"temp=":"$r"},"str",{"->":".^.s"},[{"#n":"$r1"}],"/str","/ev",{"*":".^.^.c-2","flg":18},{"s":["^Spare me further details and tell me what to do.",{"->":"$r","var":true},null]}],{"c-0":["ev",{"^->":"Theories.0.c-0.$r2"},"/ev",{"temp=":"$r"},{"->":".^.^.2.s"},[{"#n":"$r2"}],"\n",{"->":"Exactly"},{"#f":5}],"c-1":["ev",{"^->":"Theories.0.c-1.$r2"},"/ev",{"temp=":"$r"},{"->":".^.^.3.s"},[{"#n":"$r2"}],"\n",{"->":"GotThat"},{"#f":5}],"c-2":["ev",{"^->":"Theories.0.c-2.$r2"},"/ev",{"temp=":"$r"},{"->":".^.^.4.s"},[{"#n":"$r2"}],"\n",{"->":"ToDo"},{"#f":5}]}],{"#f":1}],"GotThat":[["^\"Hm, so you got him to sing the jingle, right? I catch my feed move to the rythm all the time... .\"","\n",["ev",{"^->":"GotThat.0.2.$r1"},{"temp=":"$r"},"str",{"->":".^.s"},[{"#n":"$r1"}],"/str","/ev",{"*":".^.^.c-0","flg":18},{"s":["^I think it's worth a lively whistle.",{"->":"$r","var":true},null]}],{"c-0":["ev",{"^->":"GotThat.0.c-0.$r2"},"/ev",{"temp=":"$r"},{"->":".^.^.2.s"},[{"#n":"$r2"}],"\n",{"->":"Exactly"},{"#f":5}]}],{"#f":1}],"Exactly":[["^\"Indeed! Next: the architecture of this place. The lobby looks like build yesterday, but have you seen the living space? It's a barn! Next to this shady factory building..\"","\n",["ev",{"^->":"Exactly.0.2.$r1"},{"temp=":"$r"},"str",{"->":".^.s"},[{"#n":"$r1"}],"/str","/ev",{"*":".^.^.c-0","flg":18},{"s":["^What's weird about that?",{"->":"$r","var":true},null]}],["ev",{"^->":"Exactly.0.3.$r1"},{"temp=":"$r"},"str",{"->":".^.s"},[{"#n":"$r1"}],"/str","/ev",{"*":".^.^.c-1","flg":18},{"s":["^Interesting. How about we skip this nonsense.",{"->":"$r","var":true},null]}],{"c-0":["ev",{"^->":"Exactly.0.c-0.$r2"},"/ev",{"temp=":"$r"},{"->":".^.^.2.s"},[{"#n":"$r2"}],"\n",{"->":"Weird"},{"#f":5}],"c-1":["ev",{"^->":"Exactly.0.c-1.$r2"},"/ev",{"temp=":"$r"},{"->":".^.^.3.s"},[{"#n":"$r2"}],"\n",{"->":"Offended"},{"#f":5}]}],{"#f":1}],"Weird":[["^\"This has some sentimental aura to it. Just like some movie of 2002, you got me?\"","\n",["ev",{"^->":"Weird.0.2.$r1"},{"temp=":"$r"},"str",{"->":".^.s"},[{"#n":"$r1"}],"/str","/ev",{"*":".^.^.c-0","flg":18},{"s":["^Following your thoughts feels like chasing a stranger through a cornfield at night.",{"->":"$r","var":true},null]}],["ev",{"^->":"Weird.0.3.$r1"},{"temp=":"$r"},"str",{"->":".^.s"},[{"#n":"$r1"}],"/str","/ev",{"*":".^.^.c-1","flg":18},{"s":["^Just tell me what to do.",{"->":"$r","var":true},null]}],{"c-0":["ev",{"^->":"Weird.0.c-0.$r2"},"/ev",{"temp=":"$r"},{"->":".^.^.2.s"},[{"#n":"$r2"}],"\n",{"->":"Weird2"},{"#f":5}],"c-1":["ev",{"^->":"Weird.0.c-1.$r2"},"/ev",{"temp=":"$r"},{"->":".^.^.3.s"},[{"#n":"$r2"}],"\n",{"->":"ToDo"},{"#f":5}]}],{"#f":1}],"Offended":[["^\"Well, you've asked for \"that nonsense.\" But fine.\"","\n",["ev",{"^->":"Offended.0.2.$r1"},{"temp=":"$r"},"str",{"->":".^.s"},[{"#n":"$r1"}],"/str","/ev",{"*":".^.^.c-0","flg":18},{"s":["^Continue",{"->":"$r","var":true},null]}],{"c-0":["ev",{"^->":"Offended.0.c-0.$r2"},"/ev",{"temp=":"$r"},{"->":".^.^.2.s"},[{"#n":"$r2"}],"\n",{"->":"ToDo"},{"#f":5}]}],{"#f":1}],"Weird2":[["^\"Feels to me like someone really tries to paint a picture here.. Listen, This is supposed to be a factory for dog food production. But I didnt see ANY CATTLE.\"","\n",["ev",{"^->":"Weird2.0.2.$r1"},{"temp=":"$r"},"str",{"->":".^.s"},[{"#n":"$r1"}],"/str","/ev",{"*":".^.^.c-0","flg":18},{"s":["^Yiiiieks! They ARE using carrots for dog food!",{"->":"$r","var":true},null]}],["ev",{"^->":"Weird2.0.3.$r1"},{"temp=":"$r"},"str",{"->":".^.s"},[{"#n":"$r1"}],"/str","/ev",{"*":".^.^.c-1","flg":18},{"s":["^You don't say...",{"->":"$r","var":true},null]}],{"c-0":["ev",{"^->":"Weird2.0.c-0.$r2"},"/ev",{"temp=":"$r"},{"->":".^.^.2.s"},[{"#n":"$r2"}],"\n",{"->":"DontWanneDoThisAnymore"},{"#f":5}],"c-1":["ev",{"^->":"Weird2.0.c-1.$r2"},"/ev",{"temp=":"$r"},{"->":".^.^.3.s"},[{"#n":"$r2"}],"\n",{"->":"Yes"},{"#f":5}]}],{"#f":1}],"DontWanneDoThisAnymore":[["^\"'Hrmpf', what am I talking for anyways.....\"","\n",["ev",{"^->":"DontWanneDoThisAnymore.0.2.$r1"},{"temp=":"$r"},"str",{"->":".^.s"},[{"#n":"$r1"}],"/str","/ev",{"*":".^.^.c-0","flg":18},{"s":["^Continue",{"->":"$r","var":true},null]}],{"c-0":["ev",{"^->":"DontWanneDoThisAnymore.0.c-0.$r2"},"/ev",{"temp=":"$r"},{"->":".^.^.2.s"},[{"#n":"$r2"}],"\n",{"->":"ToDo"},{"#f":5}]}],{"#f":1}],"Yes":[["^\"Yes, I do! Damn, get this whole moldy pizza...do you understand now how urgend the situation is?!\"","\n",["ev",{"^->":"Yes.0.2.$r1"},{"temp=":"$r"},"str",{"->":".^.s"},[{"#n":"$r1"}],"/str","/ev",{"*":".^.^.c-0","flg":18},{"s":["^Tell me how to get oooooooout!",{"->":"$r","var":true},null]}],{"c-0":["ev",{"^->":"Yes.0.c-0.$r2"},"/ev",{"temp=":"$r"},{"->":".^.^.2.s"},[{"#n":"$r2"}],"\n",{"->":"ToDo"},{"#f":5}]}],{"#f":1}],"ToDo":[["^\"Okay, so here's the plan: I need you to acquire an item of most value to me. It fell through these damn holes in the floor.\"","\n",["ev",{"^->":"ToDo.0.2.$r1"},{"temp=":"$r"},"str",{"->":".^.s"},[{"#n":"$r1"}],"/str","/ev",{"*":".^.^.c-0","flg":18},{"s":["^Continue",{"->":"$r","var":true},null]}],{"c-0":["ev",{"^->":"ToDo.0.c-0.$r2"},"/ev",{"temp=":"$r"},{"->":".^.^.2.s"},[{"#n":"$r2"}],"\n",{"->":"ToDo2"},{"#f":5}]}],{"#f":1}],"ToDo2":[["^\"I was showering and I wasn't fast enough to catch it. You should start your search there.\"","\n",["ev",{"^->":"ToDo2.0.2.$r1"},{"temp=":"$r"},"str",{"->":".^.s"},[{"#n":"$r1"}],"/str","/ev",{"*":".^.^.c-0","flg":18},{"s":["^Wait, that's your big plan?",{"->":"$r","var":true},null]}],{"c-0":["ev",{"^->":"ToDo2.0.c-0.$r2"},"/ev",{"temp=":"$r"},{"->":".^.^.2.s"},[{"#n":"$r2"}],"\n",{"->":"Planning"},{"#f":5}]}],{"#f":1}],"Planning":["^\"Consider this your test of worth. I reveal my plan to you if I know you're' with me. Now, Good Luck\"","\n","#","^addQuest fetch tinfoil-hat","/#","end",{"#f":1}],"#f":1}],"listDefs":{}}